MANIFEST.in
README
requirements.txt
setup.py
bin/templateparse.py
ebmas/__init__.py
water_ebmas.egg-info/PKG-INFO
water_ebmas.egg-info/SOURCES.txt
water_ebmas.egg-info/dependency_links.txt
water_ebmas.egg-info/top_level.txt
water_ebmas.egg-info/zip-safe