Metadata-Version: 1.1
Name: water-ebmas
Version: 0.2.dev1
Summary: Just test python project
Home-page: UNKNOWN
Author: LYB
Author-email: lyb10944@163.com
License: UNKNOWN
Keywords: python water-II
Platform: UNKNOWN
Classifier: Development Status :: 3 - Alpha
Classifier: Intended Audience :: Developers
Classifier: Topic :: Software Development :: Build Tools
Classifier: Programming Language :: Python :: 2.7
Classifier: Programming Language :: Python :: 3
Classifier: Programming Language :: Python :: 3.3
Classifier: Programming Language :: Python :: 3.4
Classifier: Programming Language :: Python :: 3.5
